ITS/ITU/PSeries/P2108/P2108-1.1-universal.dylib
ITS/ITU/PSeries/P2108/P2108-1.1-x64.dll
ITS/ITU/PSeries/P2108/P2108-1.1-x86.dll
ITS/ITU/PSeries/P2108/P2108-1.1-x86_64.so
ITS/ITU/PSeries/P2108/__init__.py
ITS/ITU/PSeries/P2108/p2108.py
ITS/ITU/PSeries/P2108/proplib_loader.py
proplib_p2108-1.1.0.dist-info/METADATA
proplib_p2108-1.1.0.dist-info/WHEEL
proplib_p2108-1.1.0.dist-info/licenses/LICENSE.md
proplib_p2108-1.1.0.dist-info/RECORD
