Metadata-Version: 2.4
Name: proplib-p2108
Version: 1.1.0
Summary: Python wrapper for U.S. Reference Software Implementation of Recommendation ITU-R P.2108
Project-URL: PropLib Wiki, https://ntia.github.io/propagation-library-wiki/models/P2108/
Project-URL: Python Wrapper Source, https://github.com/NTIA/p2108-python
Project-URL: Python Wrapper Bug Tracker, https://github.com/NTIA/p2108-python/issues
Project-URL: C++ Source, https://github.com/NTIA/p2108
Project-URL: NTIA GitHub, https://github.com/NTIA
Project-URL: ITS Website, https://its.ntia.gov
Author-email: The Institute for Telecommunication Sciences <code@ntia.gov>
License: # SOFTWARE DISCLAIMER / RELEASE
License-File: LICENSE.md
Keywords: ITS,ITU,NTIA,clutter,propagation,radio,telecommunications
Classifier: Intended Audience :: Science/Research
Classifier: Intended Audience :: Telecommunications Industry
Classifier: License :: Public Domain
Classifier: Natural Language :: English
Classifier: Operating System :: MacOS
Classifier: Operating System :: Microsoft :: Windows
Classifier: Operating System :: POSIX :: Linux
Classifier: Programming Language :: Python
Classifier: Programming Language :: Python :: 3
Classifier: Programming Language :: Python :: 3.9
Classifier: Programming Language :: Python :: 3.10
Classifier: Programming Language :: Python :: 3.11
Classifier: Programming Language :: Python :: 3.12
Classifier: Programming Language :: Python :: 3.13
Requires-Python: >=3.9
Provides-Extra: dev
Requires-Dist: hatchling<2.0,>=1.25.0; extra == 'dev'
Requires-Dist: p2108[tests]; extra == 'dev'
Requires-Dist: pre-commit<5.0,>=4.0.1; extra == 'dev'
Provides-Extra: tests
Requires-Dist: pytest-cov<7.0,>=6.0.0; extra == 'tests'
Requires-Dist: pytest<9.0,>=8.2.0; extra == 'tests'
